{
  "resourceType": "ValueSet",
  "id": "nyha-values",
  "url": "https://datatools4heart.eu/fhir/ValueSet/nyha-values",
  "version": "0.1",
  "name": "DataTools4Heart New York Heart Assessment Values",
  "status": "draft",
  "experimental": false,
  "date": "2023-03-07",
  "publisher": "DataTools4Heart",
  "contact": [
    {
      "name": "DataTools4Heart WP2 Team",
      "telecom": [
        {
          "system": "url",
          "value": "https://datatools4heart.eu/"
        }
      ]
    }
  ],
  "description": "Values for New York Heart Assessment",
  "compose": {
    "inactive": false,
    "include": [
      {
        "system": "http://loinc.org",
        "concept": [
          {
            "code": "LA28404-4",
            "display": "Class-I"
          },
          {
            "code": "LA28405-1",
            "display": "Class-II"
          },
          {
            "code": "LA28406-9",
            "display": "Class-III"
          },
          {
            "code": "LA28407-7",
            "display": "Class-IV"
          }
        ]
      }
    ]
  }
}
